telephone/__init__.py
telephone/main.py
telephone-0.0.5.dist-info/METADATA
telephone-0.0.5.dist-info/WHEEL
telephone-0.0.5.dist-info/top_level.txt
telephone-0.0.5.dist-info/RECORD
